to_access/__init__.py
traffic_monitor/__init__.py
traffic_monitor/tmsession.py
trafficops/__init__.py
trafficops/__version__.py
trafficops/restapi.py
trafficops/tosession.py
trafficops/utils.py
Apache_TrafficControl-3.1.0.dist-info/METADATA
Apache_TrafficControl-3.1.0.dist-info/WHEEL
Apache_TrafficControl-3.1.0.dist-info/entry_points.txt
Apache_TrafficControl-3.1.0.dist-info/top_level.txt
Apache_TrafficControl-3.1.0.dist-info/RECORD
