Metadata-Version: 2.1
Name: Apache-TrafficControl
Version: 3.1.0
Summary: Python API Client for Traffic Control
Home-page: https://trafficcontrol.apache.org/
Author: Apache Software Foundation
Author-email: dev@trafficcontrol.apache.org
License: http://www.apache.org/licenses/LICENSE-2.0
Keywords: Apache TrafficControl Traffic Control Client TrafficOps Ops
Platform: UNKNOWN
Classifier: Development Status :: 4 - Beta
Classifier: Intended Audience :: Developers
Classifier: Intended Audience :: Information Technology
Classifier: License :: OSI Approved :: Apache Software License
Classifier: Operating System :: OS Independent
Classifier: Programming Language :: Python :: 2.7
Classifier: Programming Language :: Python :: 3
Classifier: Programming Language :: Python :: 3.4
Classifier: Programming Language :: Python :: 3.5
Classifier: Programming Language :: Python :: 3.6
Classifier: Programming Language :: Python :: 3.7
Classifier: Programming Language :: Python :: 3.8
Classifier: Topic :: Database :: Front-Ends
Classifier: Topic :: Internet :: WWW/HTTP
Classifier: Topic :: Software Development :: Libraries :: Python Modules
Requires-Python: >=3.6
Requires-Dist: future (>=0.16.0)
Requires-Dist: munch (>=2.1.1)
Requires-Dist: requests (>=2.26.0)
Provides-Extra: dev
Requires-Dist: pylint (<3.0,>=2.0) ; extra == 'dev'
